{"zNodes":[
	{"id":0,"pId":0,"name":"FireStorm","title":"","detail":"firestorm.html"},
	{"id":1,"pId":0,"name":"Java","title":"","detail":""},
	{"id":2,"pId":0,"name":"HTML","title":"","detail":""},
	{"id":3,"pId":0,"name":"JavaScript","title":"","detail":""},
	{"id":4,"pId":0,"name":"工具","title":"","detail":""},
	{"id":5,"pId":0,"name":"js特效","title":"","detail":""},
	{"id":6,"pId":0,"name":"eclipse设置","title":"","detail":""},
	{"id":7,"pId":0,"name":"学习总结","title":"","detail":""},
	{"id":8,"pId":0,"name":"数据库","title":"","detail":""}
	
]}